pytest_dictsdiff.py
pytest_dictsdiff-0.5.8.dist-info/METADATA
pytest_dictsdiff-0.5.8.dist-info/WHEEL
pytest_dictsdiff-0.5.8.dist-info/entry_points.txt
pytest_dictsdiff-0.5.8.dist-info/top_level.txt
pytest_dictsdiff-0.5.8.dist-info/RECORD
