Metadata-Version: 2.1
Name: pytest-dictsdiff
Version: 0.5.8
Summary: UNKNOWN
Home-page: UNKNOWN
Author: Lukasz Balcerzak
Author-email: lukaszbalcerzak@gmail.com
License: MIT
Platform: UNKNOWN
Classifier: Framework :: Pytest
Requires-Dist: dictdiffer
